v8bot/API.py
v8bot/__init__.py
v8bot-0.0.14.data/scripts/v8b
v8bot-0.0.14.dist-info/DESCRIPTION.rst
v8bot-0.0.14.dist-info/METADATA
v8bot-0.0.14.dist-info/RECORD
v8bot-0.0.14.dist-info/WHEEL
v8bot-0.0.14.dist-info/dependency_links.txt
v8bot-0.0.14.dist-info/metadata.json
v8bot-0.0.14.dist-info/top_level.txt
