Metadata-Version: 2.0
Name: v8bot
Version: 0.0.14
Summary: write bots for Hitbox.tv in JavaScript
Home-page: https://bitbucket.org/uranoxyd/v8bot
Author: David Ewelt
Author-email: uranoxyd@gmail.com
License: BSD
Platform: UNKNOWN
Classifier: Development Status :: 3 - Alpha
Classifier: Programming Language :: Python :: 2
Classifier: Programming Language :: Python :: 2.7
Requires-Dist: hitboxy[chatclient] (>=0.1.23)
